LICENSE
README.md
setup.py
notion_scraper.egg-info/PKG-INFO
notion_scraper.egg-info/SOURCES.txt
notion_scraper.egg-info/dependency_links.txt
notion_scraper.egg-info/requires.txt
notion_scraper.egg-info/top_level.txt
pypi_scraper/__init__.py